geti_sdk/__init__.py
geti_sdk/_version.py
geti_sdk/geti.py
geti_sdk/platform_versions.py
geti_sdk/annotation_readers/__init__.py
geti_sdk/annotation_readers/base_annotation_reader.py
geti_sdk/annotation_readers/directory_tree_annotation_reader.py
geti_sdk/annotation_readers/geti_annotation_reader.py
geti_sdk/benchmarking/__init__.py
geti_sdk/benchmarking/benchmarker.py
geti_sdk/benchmarking/utils.py
geti_sdk/data_models/__init__.py
geti_sdk/data_models/algorithms.py
geti_sdk/data_models/annotation_scene.py
geti_sdk/data_models/annotations.py
geti_sdk/data_models/code_deployment_info.py
geti_sdk/data_models/configurable_parameter.py
geti_sdk/data_models/configurable_parameter_group.py
geti_sdk/data_models/configuration.py
geti_sdk/data_models/configuration_identifiers.py
geti_sdk/data_models/credit_system.py
geti_sdk/data_models/dataset.py
geti_sdk/data_models/job.py
geti_sdk/data_models/label.py
geti_sdk/data_models/media.py
geti_sdk/data_models/media_identifiers.py
geti_sdk/data_models/model.py
geti_sdk/data_models/model_group.py
geti_sdk/data_models/performance.py
geti_sdk/data_models/predictions.py
geti_sdk/data_models/project.py
geti_sdk/data_models/shapes.py
geti_sdk/data_models/status.py
geti_sdk/data_models/task.py
geti_sdk/data_models/task_annotation_state.py
geti_sdk/data_models/test_result.py
geti_sdk/data_models/user.py
geti_sdk/data_models/utils.py
geti_sdk/data_models/configuration_models/__init__.py
geti_sdk/data_models/configuration_models/project_configuration.py
geti_sdk/data_models/configuration_models/training_configuration.py
geti_sdk/data_models/configuration_models/hyperparameters/__init__.py
geti_sdk/data_models/configuration_models/hyperparameters/augmentation.py
geti_sdk/data_models/configuration_models/hyperparameters/hyperparameters.py
geti_sdk/data_models/containers/__init__.py
geti_sdk/data_models/containers/algorithm_list.py
geti_sdk/data_models/containers/label_list.py
geti_sdk/data_models/containers/media_list.py
geti_sdk-2.13.1.dist-info/METADATA
geti_sdk-2.13.1.dist-info/WHEEL
geti_sdk-2.13.1.dist-info/licenses/CODE_OF_CONDUCT.md
geti_sdk-2.13.1.dist-info/licenses/LICENSE
geti_sdk-2.13.1.dist-info/RECORD
