Metadata-Version: 2.4
Name: geti-sdk
Version: 2.13.1
Summary: Software Development Kit for the Geti™ platform
Project-URL: Documentation, https://docs.geti.intel.com/
Project-URL: Repository, https://github.com/open-edge-platform/geti-sdk
Project-URL: Issues, https://github.com/open-edge-platform/geti-sdk/issues
Project-URL: Changelog, https://github.com/open-edge-platform/geti-sdk/releases
Author: Intel Corporation
Maintainer-email: Leonardo Lai <leonardo.lai@intel.com>, Alexander Barabanov <alexander.barabanov@intel.com>
License-File: CODE_OF_CONDUCT.md
License-File: LICENSE
Keywords: computer vision,deep learning,geti,intel,machine learning
Classifier: Development Status :: 5 - Production/Stable
Classifier: License :: OSI Approved :: Apache Software License
Classifier: Operating System :: OS Independent
Classifier: Programming Language :: Python :: 3
Requires-Python: <=3.13,>=3.10
Requires-Dist: attrs~=25.3
Requires-Dist: certifi~=2025.11.12
Requires-Dist: cryptography~=46.0
Requires-Dist: defusedxml~=0.7
Requires-Dist: imageio-ffmpeg~=0.6
Requires-Dist: joblib~=1.5
Requires-Dist: numpy~=2.1
Requires-Dist: omegaconf~=2.3
Requires-Dist: opencv-python~=4.11
Requires-Dist: openvino-model-api~=0.3
Requires-Dist: openvino~=2025.2
Requires-Dist: orjson~=3.10
Requires-Dist: ovmsclient~=2023.1
Requires-Dist: pathvalidate~=3.3
Requires-Dist: pillow~=12.0
Requires-Dist: pydantic==2.12.4
Requires-Dist: python-dotenv~=1.1
Requires-Dist: requests~=2.32
Requires-Dist: semver~=3.0
Requires-Dist: simplejson~=3.20
Requires-Dist: tqdm~=4.67
Requires-Dist: urllib3~=2.5
Provides-Extra: docs
Requires-Dist: myst-parser~=2.0; extra == 'docs'
Requires-Dist: sphinx-rtd-theme~=1.3; extra == 'docs'
Requires-Dist: sphinx~=7.2; extra == 'docs'
Provides-Extra: notebooks
Requires-Dist: ipywidgets~=8.1; extra == 'notebooks'
Requires-Dist: jupyter-core>=5.8.1; extra == 'notebooks'
Requires-Dist: jupyterlab~=4.4; extra == 'notebooks'
Requires-Dist: mistune~=2.0; extra == 'notebooks'
Requires-Dist: pandas~=2.3; extra == 'notebooks'
